watson/__init__.py
watson/filters/__init__.py
watson/filters/abc.py
watson/filters/string.py
watson_filters-1.0.1.dist-info/DESCRIPTION.rst
watson_filters-1.0.1.dist-info/METADATA
watson_filters-1.0.1.dist-info/RECORD
watson_filters-1.0.1.dist-info/WHEEL
watson_filters-1.0.1.dist-info/metadata.json
watson_filters-1.0.1.dist-info/top_level.txt
