Metadata-Version: 2.0
Name: watson-filters
Version: 1.0.1
Summary: Modify and convert values into something else.
Home-page: http://github.com/watsonpy/watson-filters
Author: Simon Coulton
Author-email: simon@bespohk.com
License: Copyright (c) 2012-2016 Bespohk, and is maintained by multiple
Requires-Dist: watson-html (>=1.0.0)
Provides-Extra: test
Requires-Dist: coverage; extra == 'test'
Requires-Dist: coveralls; extra == 'test'
Requires-Dist: pytest; extra == 'test'
Requires-Dist: pytest-cov; extra == 'test'
